ganimede/__init__.py
ganimede/main.py
ganimede/managers/Cell.py
ganimede/managers/Comms.py
ganimede/managers/ConfigManager.py
ganimede/managers/Kernel.py
ganimede/managers/Notebook.py
ganimede/managers/RouteManager.py
ganimede/managers/__init__.py
ganimede/ui_dist/codicon.ttf
ganimede/ui_dist/favicon.png
ganimede/ui_dist/index.html
ganimede/ui_dist/assets/Active4D-c3005ee9.js
ganimede/ui_dist/assets/abap-b43a89e6.js
ganimede/ui_dist/assets/apex-937df311.js
ganimede/ui_dist/assets/azcli-282bdb58.js
ganimede/ui_dist/assets/bat-3e233203.js
ganimede/ui_dist/assets/bicep-a145af43.js
ganimede/ui_dist/assets/cameligo-06e900e4.js
ganimede/ui_dist/assets/clojure-db811a57.js
ganimede/ui_dist/assets/codicon-71cccbf1.ttf
ganimede/ui_dist/assets/coffee-09967f6c.js
ganimede/ui_dist/assets/cpp-faa9e9b6.js
ganimede/ui_dist/assets/csharp-97f4fb7d.js
ganimede/ui_dist/assets/csp-a35669e2.js
ganimede/ui_dist/assets/css-2476f175.js
ganimede/ui_dist/assets/cssMode-a26187c5.js
ganimede/ui_dist/assets/cssMode-cd92233a.js
ganimede/ui_dist/assets/cypher-303c3469.js
ganimede/ui_dist/assets/dart-49550748.js
ganimede/ui_dist/assets/dockerfile-f0d559c9.js
ganimede/ui_dist/assets/ecl-8f371079.js
ganimede/ui_dist/assets/editor.main-a242252f.js
ganimede/ui_dist/assets/editor.main-bbfb5468.js
ganimede/ui_dist/assets/editor.worker-df55e1ff.js
ganimede/ui_dist/assets/elixir-8520cbc3.js
ganimede/ui_dist/assets/flow9-21ceb8bd.js
ganimede/ui_dist/assets/freemarker2-145d781a.js
ganimede/ui_dist/assets/freemarker2-b82fc772.js
ganimede/ui_dist/assets/fsharp-2e782b00.js
ganimede/ui_dist/assets/go-606d7332.js
ganimede/ui_dist/assets/graphql-503141bc.js
ganimede/ui_dist/assets/handlebars-6c5a96ac.js
ganimede/ui_dist/assets/handlebars-6fe4a310.js
ganimede/ui_dist/assets/hcl-41af7310.js
ganimede/ui_dist/assets/html-6fdc0839.js
ganimede/ui_dist/assets/html-db694a72.js
ganimede/ui_dist/assets/htmlMode-598cac03.js
ganimede/ui_dist/assets/htmlMode-a479cb30.js
ganimede/ui_dist/assets/index-7e4408f1.css
ganimede-0.2.dist-info/METADATA
ganimede-0.2.dist-info/WHEEL
ganimede-0.2.dist-info/entry_points.txt
ganimede-0.2.dist-info/top_level.txt
ganimede-0.2.dist-info/RECORD
