Metadata-Version: 2.1
Name: ganimede
Version: 0.2
Summary: A Rethinking of Computational Notebooks
Author: nottherealsanta
Requires-Python: >=3.8
Requires-Dist: jupyter-client >=7.4.9
Requires-Dist: starlette >=0.23.1
Requires-Dist: pandas >=1.5.3
Requires-Dist: black >=23.1.0
Requires-Dist: ipykernel >=6.20.2
Requires-Dist: uvicorn >=0.20.0
Requires-Dist: rich >=13.2.0
Requires-Dist: websockets >=11.0.3
Requires-Dist: ypy-websocket ==0.12.1
Requires-Dist: click ==8.1.3
